biosimulators_boolnet/__init__.py
biosimulators_boolnet/__main__.py
biosimulators_boolnet/_version.py
biosimulators_boolnet/config.py
biosimulators_boolnet/core.py
biosimulators_boolnet/data_model.py
biosimulators_boolnet/utils.py
biosimulators_boolnet-0.1.18.dist-info/LICENSE
biosimulators_boolnet-0.1.18.dist-info/METADATA
biosimulators_boolnet-0.1.18.dist-info/WHEEL
biosimulators_boolnet-0.1.18.dist-info/entry_points.txt
biosimulators_boolnet-0.1.18.dist-info/top_level.txt
biosimulators_boolnet-0.1.18.dist-info/RECORD
