Metadata-Version: 2.1
Name: biosimulators-boolnet
Version: 0.1.18
Summary: BioSimulators-compliant command-line interface to the BoolNet simulation program.
Home-page: https://github.com/biosimulators/Biosimulators_BoolNet
Author: BioSimulators Team
Author-email: info@biosimulators.org
License: MIT
Download-URL: https://github.com/biosimulators/Biosimulators_BoolNet
Keywords: systems biology,computational biology,logical model,numerical simulation,BioSimulators,SBML,SED-ML,COMBINE,OMEX,BoolNet
Platform: UNKNOWN
Classifier: Development Status :: 3 - Alpha
Classifier: Intended Audience :: Science/Research
Classifier: License :: OSI Approved :: MIT License
Classifier: Topic :: Scientific/Engineering :: Bio-Informatics
License-File: LICENSE
Requires-Dist: biosimulators-utils[logging,sbml] (>=0.1.122)
Requires-Dist: kisao
Requires-Dist: lxml
Requires-Dist: numpy
Requires-Dist: rpy2
Provides-Extra: all
Requires-Dist: biosimulators-utils[containers] ; extra == 'all'
Requires-Dist: python-dateutil ; extra == 'all'
Requires-Dist: pyyaml ; extra == 'all'
Provides-Extra: docs
Provides-Extra: tests
Requires-Dist: biosimulators-utils[containers] ; extra == 'tests'
Requires-Dist: python-dateutil ; extra == 'tests'
Requires-Dist: pyyaml ; extra == 'tests'
